uscg_leetcode_validator/__init__.py
uscg_leetcode_validator/main.py
uscg_leetcode_validator/test.py
uscg_leetcode_validator-1.0.6.dist-info/METADATA
uscg_leetcode_validator-1.0.6.dist-info/WHEEL
uscg_leetcode_validator-1.0.6.dist-info/entry_points.txt
uscg_leetcode_validator-1.0.6.dist-info/top_level.txt
uscg_leetcode_validator-1.0.6.dist-info/RECORD
