Metadata-Version: 2.4
Name: uscg_leetcode_validator
Version: 1.0.6
Summary: Used to validate restricted python code inputs against test cases.
Author: Jacob Elliott
Author-email: coachelliott@uscybergames.org
Classifier: Programming Language :: Python :: 3
Classifier: Operating System :: OS Independent
Requires-Python: >=3.6
Dynamic: author
Dynamic: author-email
Dynamic: classifier
Dynamic: description
Dynamic: description-content-type
Dynamic: requires-python
Dynamic: summary
